LICENSE
MANIFEST.in
README.md
setup.cfg
setup.py
distributions/__init__.py
distributions/admin.py
distributions/apis.py
distributions/apps.py
distributions/models.py
distributions/serializers.py
distributions/tests.py
distributions/urls.py
distributions/views.py
distributions/migrations/__init__.py
distributions/static/distributions/wx.png
distributions/static/distributions/dist/app.js
distributions/static/distributions/src/app.js
distributions/templates/distributions/index.html
django_distributions.egg-info/PKG-INFO
django_distributions.egg-info/SOURCES.txt
django_distributions.egg-info/dependency_links.txt
django_distributions.egg-info/top_level.txt